setup.py
django_easy_auth.egg-info/PKG-INFO
django_easy_auth.egg-info/SOURCES.txt
django_easy_auth.egg-info/dependency_links.txt
django_easy_auth.egg-info/top_level.txt
easy_auth/__init__.py
easy_auth/admin.py
easy_auth/apps.py
easy_auth/models.py
easy_auth/urls.py
easy_auth/views.py