Metadata-Version: 1.0
Name: django-easy-auth
Version: 1.0.1
Summary: This app allows you drop in user authentication functionality using Django's built in views.
Home-page: https://github.com/seanwiseman/django-easy-auth
Author: Sean Wiseman
Author-email: seanwiseman2012@gmail.com
License: MIT
Platform: UNKNOWN
